{
  "status": "sprint_1_complete",
  "last_task": "sprint_2_planning",
  "next_step": "sprint_2_implementation",
  "decisions": [
    "D1-camera: Camera2D fixa centralizada no grid, zoom por pinch 0.5x-4x, sem pan nem follow",
    "D2-main_scene: project.godot aponta para combat_scene.tscn, main_scene.tscn eliminada",
    "D3-wiring: combat_scene.gd (script da cena raiz) faz conversao screen->world->grid->teleport",
    "D4-grid: var grid_size Vector2i padrao 8x8, data-driven via setup(), tamanho por JSON",
    "D5-input: Android touch apenas, InputEventScreenTouch e InputEventScreenDrag, sem mouse/teclado",
    "D6-placeholders: tile-livre=cinza-claro, tile-bloqueado=vermelho-escuro, highlight=amarelo-translucido, heroi=circulo-azul, todos via _draw()",
    "D7-pinch_fix: TouchController emite screen_tapped apenas no released, cancela se 2o dedo aparecer",
    "D8-movement: hero move_along_path animado via Tween, tile a tile, com delay entre passos",
    "D9-path_display: tiles do caminho A* sao destacados (highlight path) antes do hero se mover",
    "D10-reach_range: BFS de tiles alcancaveis exibido ao tocar no hero (range definido no JSON)",
    "D11-obstacles: cells bloqueadas definidas em data/combat/scenario_01.json, carregadas no setup()"
  ],
  "completed_sprints": [1],
  "current_sprint": 2
}
